{
  "entries": {
    "tap": {
      "ethereum/ethereum": {
        "revision": "becf5cf3dd9fb166ba7e1d17f70b766c7848cd6b"
      },
      "extrawurst/tap": {
        "revision": "7274e63c0f2ee6685fc28c8f61d87594a2086d55"
      },
      "github/gh": {
        "revision": "209f59cda890de69b74c224982591642c21323d3"
      },
      "homebrew/cask": {
        "revision": "b763979ebd71b17de16717aa6e5aba29bdef6f89"
      },
      "homebrew/cask-fonts": {
        "revision": "de82e5c295491dd0abc0275f04cc2dc1504b8009"
      },
      "koekeishiya/formulae": {
        "revision": "399a882864581dbb9f003ee5ce1d00b2f438695d"
      },
      "wix/brew": {
        "revision": "55b23679c79ce928006974ccc1706a7819746627"
      },
      "homebrew/services": {
        "revision": "31bb79235694bdd39143843fae37bdfb297cc5cd"
      }
    },
    "brew": {
      "asdf": {
        "version": "0.8.0_1",
        "bottle": false
      },
      "applesimutils": {
        "version": "0.9.2",
        "bottle": {
          "rebuild": 0,
          "cellar": "/usr/local/Cellar",
          "prefix": "/usr/local",
          "root_url": "https://github.com/wix/AppleSimulatorUtils/releases/download/0.9.2",
          "files": {
            "catalina": {
              "url": "https://github.com/wix/AppleSimulatorUtils/releases/download/0.9.2/applesimutils-0.9.2.catalina.bottle.tar.gz",
              "sha256": "11c57fb0008b59552881f03d6897de54ad4e7046cb19ff26725ce34d3a6c1738"
            },
            "mojave": {
              "url": "https://github.com/wix/AppleSimulatorUtils/releases/download/0.9.2/applesimutils-0.9.2.mojave.bottle.tar.gz",
              "sha256": "11c57fb0008b59552881f03d6897de54ad4e7046cb19ff26725ce34d3a6c1738"
            },
            "high_sierra": {
              "url": "https://github.com/wix/AppleSimulatorUtils/releases/download/0.9.2/applesimutils-0.9.2.high_sierra.bottle.tar.gz",
              "sha256": "11c57fb0008b59552881f03d6897de54ad4e7046cb19ff26725ce34d3a6c1738"
            },
            "sierra": {
              "url": "https://github.com/wix/AppleSimulatorUtils/releases/download/0.9.2/applesimutils-0.9.2.sierra.bottle.tar.gz",
              "sha256": "11c57fb0008b59552881f03d6897de54ad4e7046cb19ff26725ce34d3a6c1738"
            },
            "big_sur": {
              "url": "https://github.com/wix/AppleSimulatorUtils/releases/download/0.9.2/applesimutils-0.9.2.big_sur.bottle.tar.gz",
              "sha256": "11c57fb0008b59552881f03d6897de54ad4e7046cb19ff26725ce34d3a6c1738"
            },
            "arm64_big_sur": {
              "url": "https://github.com/wix/AppleSimulatorUtils/releases/download/0.9.2/applesimutils-0.9.2.arm64_big_sur.bottle.tar.gz",
              "sha256": "11c57fb0008b59552881f03d6897de54ad4e7046cb19ff26725ce34d3a6c1738"
            }
          }
        }
      },
      "bat": {
        "version": "0.18.0",
        "bottle": {
          "rebuild": 0,
          "cellar": ":any_skip_relocation",
          "prefix": "/usr/local",
          "root_url": "https://homebrew.bintray.com/bottles",
          "files": {
            "arm64_big_sur": {
              "url": "https://homebrew.bintray.com/bottles/bat-0.18.0.arm64_big_sur.bottle.tar.gz",
              "sha256": "9bbb0e82789791a64d355373fe297f0f4e3cffa229583a352d34a2b5e561025e"
            },
            "big_sur": {
              "url": "https://homebrew.bintray.com/bottles/bat-0.18.0.big_sur.bottle.tar.gz",
              "sha256": "3665b461a7e64ff8fbd67d64ee43b1f59446087c9551b78954713602d3c0a67d"
            },
            "catalina": {
              "url": "https://homebrew.bintray.com/bottles/bat-0.18.0.catalina.bottle.tar.gz",
              "sha256": "d69cf5c91d2b62c76dd9e61a6fc68c6cd8c132dee4505af4f3f8677dd056436f"
            },
            "mojave": {
              "url": "https://homebrew.bintray.com/bottles/bat-0.18.0.mojave.bottle.tar.gz",
              "sha256": "ec1adbd7c9a6921dce69e7a538187f38a178dcd755c153cd9721d3603f052050"
            }
          }
        }
      },
      "cocoapods": {
        "version": "1.10.1",
        "bottle": {
          "rebuild": 0,
          "cellar": "/usr/local/Cellar",
          "prefix": "/usr/local",
          "root_url": "https://homebrew.bintray.com/bottles",
          "files": {
            "arm64_big_sur": {
              "url": "https://homebrew.bintray.com/bottles/cocoapods-1.10.1.arm64_big_sur.bottle.tar.gz",
              "sha256": "08794cfd260bf206eed3496805816661da367bffdf9af748cd812b1c40a0de75"
            },
            "big_sur": {
              "url": "https://homebrew.bintray.com/bottles/cocoapods-1.10.1.big_sur.bottle.tar.gz",
              "sha256": "0caa8953926c827f62d53f9767aed0a904604c0425ea0557b24d738240db809a"
            },
            "catalina": {
              "url": "https://homebrew.bintray.com/bottles/cocoapods-1.10.1.catalina.bottle.tar.gz",
              "sha256": "3a05cecba1a15c8cad8baa04b4e6be6eef8159c061b37096012de75132e7cd74"
            },
            "mojave": {
              "url": "https://homebrew.bintray.com/bottles/cocoapods-1.10.1.mojave.bottle.tar.gz",
              "sha256": "0883b18c75e7cade594eced3d828ccacefafbbb3ead61667bca21e1fbc94970d"
            }
          }
        }
      },
      "coreutils": {
        "version": "8.32",
        "bottle": {
          "rebuild": 2,
          "cellar": "/usr/local/Cellar",
          "prefix": "/usr/local",
          "root_url": "https://homebrew.bintray.com/bottles",
          "files": {
            "arm64_big_sur": {
              "url": "https://homebrew.bintray.com/bottles/coreutils-8.32.arm64_big_sur.bottle.2.tar.gz",
              "sha256": "e7d88d2b7a91a57dfd37c2ea14752d1bb116f25694eab1161d6e8088f7db5921"
            },
            "big_sur": {
              "url": "https://homebrew.bintray.com/bottles/coreutils-8.32.big_sur.bottle.2.tar.gz",
              "sha256": "371ec57703b3646e0113331308b6e03617c2a7f91e15e113380b605455daba20"
            },
            "catalina": {
              "url": "https://homebrew.bintray.com/bottles/coreutils-8.32.catalina.bottle.2.tar.gz",
              "sha256": "7a97ad96dfbe6abbb5c94424518a077e040af8a77d1946ca960a5f33cd237551"
            },
            "mojave": {
              "url": "https://homebrew.bintray.com/bottles/coreutils-8.32.mojave.bottle.2.tar.gz",
              "sha256": "10fbad2e35846c7e835cb979b5beb9edf07f3a9742ddcc3c28d9abd5fe9ccb1b"
            }
          }
        }
      },
      "curl": {
        "version": "7.75.0",
        "bottle": {
          "rebuild": 0,
          "cellar": ":any",
          "prefix": "/usr/local",
          "root_url": "https://homebrew.bintray.com/bottles",
          "files": {
            "arm64_big_sur": {
              "url": "https://homebrew.bintray.com/bottles/curl-7.75.0.arm64_big_sur.bottle.tar.gz",
              "sha256": "feef288ebc2fb55c4c0803e233c600b5ded8e92863f0ad3a058c9c007933940b"
            },
            "big_sur": {
              "url": "https://homebrew.bintray.com/bottles/curl-7.75.0.big_sur.bottle.tar.gz",
              "sha256": "04b809e93240c4b79bad7d224756492a574e6f97e78d2b394cb7418b633d5c7d"
            },
            "catalina": {
              "url": "https://homebrew.bintray.com/bottles/curl-7.75.0.catalina.bottle.tar.gz",
              "sha256": "f06f0f2a005d444c23cdaec96f047a204cb024ee881213682ab3374f1d1f4dbd"
            },
            "mojave": {
              "url": "https://homebrew.bintray.com/bottles/curl-7.75.0.mojave.bottle.tar.gz",
              "sha256": "ebcf2c049613a0655429872b1bd109b1dd00ba1721e6356cf2aec8b95ba37e47"
            }
          }
        }
      },
      "ethereum": {
        "version": "1.10.0",
        "bottle": {
          "rebuild": 0,
          "cellar": ":any_skip_relocation",
          "prefix": "/usr/local",
          "root_url": "https://homebrew.bintray.com/bottles",
          "files": {
            "arm64_big_sur": {
              "url": "https://homebrew.bintray.com/bottles/ethereum-1.10.0.arm64_big_sur.bottle.tar.gz",
              "sha256": "9210769c0db416007d4c527988ec141b6f8e94df104ee9f5a27c0200e22cc7cf"
            },
            "big_sur": {
              "url": "https://homebrew.bintray.com/bottles/ethereum-1.10.0.big_sur.bottle.tar.gz",
              "sha256": "3b6e9af32e3633328aa807a25be3c7a065dd4469d85d8f5ac8221c2278689a23"
            },
            "catalina": {
              "url": "https://homebrew.bintray.com/bottles/ethereum-1.10.0.catalina.bottle.tar.gz",
              "sha256": "838dc89173fed12283334907e07357c0b647a94ff7cdeebdb6dcccf3f2a7589d"
            },
            "mojave": {
              "url": "https://homebrew.bintray.com/bottles/ethereum-1.10.0.mojave.bottle.tar.gz",
              "sha256": "f7c5d947f01046be88a2e93311a5fa09749e3859d42a7cf04eb271064027002e"
            }
          }
        }
      },
      "exa": {
        "version": "0.9.0_2",
        "bottle": {
          "rebuild": 0,
          "cellar": ":any_skip_relocation",
          "prefix": "/usr/local",
          "root_url": "https://homebrew.bintray.com/bottles",
          "files": {
            "arm64_big_sur": {
              "url": "https://homebrew.bintray.com/bottles/exa-0.9.0_2.arm64_big_sur.bottle.tar.gz",
              "sha256": "b5fc2d5300cbd6ab2d3c113ce011c6ac187e8e774f3d3e4d1f1592b109206d39"
            },
            "big_sur": {
              "url": "https://homebrew.bintray.com/bottles/exa-0.9.0_2.big_sur.bottle.tar.gz",
              "sha256": "2ea88382cf3e9906bc27cd37f3f57c953cce9fcd686d958824ccb27093c5c8da"
            },
            "catalina": {
              "url": "https://homebrew.bintray.com/bottles/exa-0.9.0_2.catalina.bottle.tar.gz",
              "sha256": "979193384c57b8858b592d1200468cb6584ffa7df7833d6777eb8637e0ecfc97"
            },
            "mojave": {
              "url": "https://homebrew.bintray.com/bottles/exa-0.9.0_2.mojave.bottle.tar.gz",
              "sha256": "af7d2f089dc99cab221dbc57c33c443e112a843911d561588621e60378f56a46"
            }
          }
        }
      },
      "gh": {
        "version": "1.7.0",
        "bottle": {
          "rebuild": 0,
          "cellar": ":any_skip_relocation",
          "prefix": "/usr/local",
          "root_url": "https://homebrew.bintray.com/bottles",
          "files": {
            "arm64_big_sur": {
              "url": "https://homebrew.bintray.com/bottles/gh-1.7.0.arm64_big_sur.bottle.tar.gz",
              "sha256": "1575fad6e5dda0241957d4668b04802df7d5a963a93d213471f5f89730d1e260"
            },
            "big_sur": {
              "url": "https://homebrew.bintray.com/bottles/gh-1.7.0.big_sur.bottle.tar.gz",
              "sha256": "88ab0ed37b4050437aaaac46fb444a001b86b024afd04f9926c5f479d44d6a7b"
            },
            "catalina": {
              "url": "https://homebrew.bintray.com/bottles/gh-1.7.0.catalina.bottle.tar.gz",
              "sha256": "9399e8ca6bb5c0621c06d3963e28db01a9de4074f729054315a048272de3555d"
            },
            "mojave": {
              "url": "https://homebrew.bintray.com/bottles/gh-1.7.0.mojave.bottle.tar.gz",
              "sha256": "c0dc5b0ddd5a30880be8e162bf9c2cc51f7057707204ae2af3b999715d371537"
            }
          }
        }
      },
      "git": {
        "version": "2.30.1",
        "bottle": {
          "rebuild": 0,
          "cellar": "/usr/local/Cellar",
          "prefix": "/usr/local",
          "root_url": "https://homebrew.bintray.com/bottles",
          "files": {
            "arm64_big_sur": {
              "url": "https://homebrew.bintray.com/bottles/git-2.30.1.arm64_big_sur.bottle.tar.gz",
              "sha256": "53c147ae99043706072a5ada0ecf764a8f386fb4f3afa7aa20546cc33a349d84"
            },
            "big_sur": {
              "url": "https://homebrew.bintray.com/bottles/git-2.30.1.big_sur.bottle.tar.gz",
              "sha256": "c0be5c5895bd3a85bd83953fd9f6fec3864d8ea419b4678b43afaac7217b9853"
            },
            "catalina": {
              "url": "https://homebrew.bintray.com/bottles/git-2.30.1.catalina.bottle.tar.gz",
              "sha256": "0dd5f43dc263da3d87a83216392fedd96774bd0c9f89e2dc717c549b1803e8d6"
            },
            "mojave": {
              "url": "https://homebrew.bintray.com/bottles/git-2.30.1.mojave.bottle.tar.gz",
              "sha256": "c84740ee72f1909fe019bba32ccf265b393df5c2fbd5d31886cca5904928f1b9"
            }
          }
        }
      },
      "grep": {
        "version": "3.6",
        "bottle": {
          "rebuild": 0,
          "cellar": ":any",
          "prefix": "/usr/local",
          "root_url": "https://homebrew.bintray.com/bottles",
          "files": {
            "arm64_big_sur": {
              "url": "https://homebrew.bintray.com/bottles/grep-3.6.arm64_big_sur.bottle.tar.gz",
              "sha256": "a48ab26324b25a6033372f26490b09e7e0569f76a4b7f85bdd0aa9a3fc996537"
            },
            "big_sur": {
              "url": "https://homebrew.bintray.com/bottles/grep-3.6.big_sur.bottle.tar.gz",
              "sha256": "6ee2dac30a5250d7d218b6520392b4cb8e7a806149f900e11637e556e6a9237a"
            },
            "catalina": {
              "url": "https://homebrew.bintray.com/bottles/grep-3.6.catalina.bottle.tar.gz",
              "sha256": "78c2b965ced34a99ac47d3058a3971b9696a6157215c82edd16562d6ec6fc689"
            },
            "mojave": {
              "url": "https://homebrew.bintray.com/bottles/grep-3.6.mojave.bottle.tar.gz",
              "sha256": "80a62eaefb57437bcb3aeb1d8489b9bf062ec77184624249da27afc578be1315"
            },
            "high_sierra": {
              "url": "https://homebrew.bintray.com/bottles/grep-3.6.high_sierra.bottle.tar.gz",
              "sha256": "ae3cfbe66d6391edd32153f9b02e3da1286482dd196a18da017903a0bd4e7cf7"
            }
          }
        }
      },
      "htop": {
        "version": "3.0.5",
        "bottle": {
          "rebuild": 0,
          "cellar": ":any",
          "prefix": "/usr/local",
          "root_url": "https://homebrew.bintray.com/bottles",
          "files": {
            "arm64_big_sur": {
              "url": "https://homebrew.bintray.com/bottles/htop-3.0.5.arm64_big_sur.bottle.tar.gz",
              "sha256": "e2b32da2189775e5a303b948bf2bf86224f2850786e849371efe002402f26c6f"
            },
            "big_sur": {
              "url": "https://homebrew.bintray.com/bottles/htop-3.0.5.big_sur.bottle.tar.gz",
              "sha256": "8f4e4c5d0ee34c41e008bb9a2ed4331303a42bd594ac358a822604a145c868ea"
            },
            "catalina": {
              "url": "https://homebrew.bintray.com/bottles/htop-3.0.5.catalina.bottle.tar.gz",
              "sha256": "7dc2bf8825918876e3a853acbc9d7045786d1d418fdae2b0a4e6d4500006a08e"
            },
            "mojave": {
              "url": "https://homebrew.bintray.com/bottles/htop-3.0.5.mojave.bottle.tar.gz",
              "sha256": "a009b141dcf7b95c60da3ef685ea0736be0c0a5e1e0de0945153697c6a032e2a"
            }
          }
        }
      },
      "ios-deploy": {
        "version": "1.11.4",
        "bottle": {
          "rebuild": 0,
          "cellar": ":any_skip_relocation",
          "prefix": "/usr/local",
          "root_url": "https://homebrew.bintray.com/bottles",
          "files": {
            "arm64_big_sur": {
              "url": "https://homebrew.bintray.com/bottles/ios-deploy-1.11.4.arm64_big_sur.bottle.tar.gz",
              "sha256": "e85b52bd030eef2dfdc3f354fd4850fc6a09391e2822f48a1de8fed4d3581a4d"
            },
            "big_sur": {
              "url": "https://homebrew.bintray.com/bottles/ios-deploy-1.11.4.big_sur.bottle.tar.gz",
              "sha256": "b4490b2ef74d1e2b498bf9a5e79305dacbd2bed3c5e0dd6b93822e19953f2074"
            },
            "catalina": {
              "url": "https://homebrew.bintray.com/bottles/ios-deploy-1.11.4.catalina.bottle.tar.gz",
              "sha256": "23244feccb6cf78da5eb83163c6a187acc3aa8248fa34eb909e1728b4876e5bb"
            },
            "mojave": {
              "url": "https://homebrew.bintray.com/bottles/ios-deploy-1.11.4.mojave.bottle.tar.gz",
              "sha256": "2a5a3fd9d3288d48a75f4f85aaf72e98d0866edca7c5b56ba6d2ccf0d98e96b8"
            }
          }
        }
      },
      "jq": {
        "version": "1.6",
        "bottle": {
          "rebuild": 1,
          "cellar": ":any",
          "prefix": "/usr/local",
          "root_url": "https://homebrew.bintray.com/bottles",
          "files": {
            "arm64_big_sur": {
              "url": "https://homebrew.bintray.com/bottles/jq-1.6.arm64_big_sur.bottle.1.tar.gz",
              "sha256": "674b3ae41c399f1e8e44c271b0e6909babff9fcd2e04a2127d25e2407ea4dd33"
            },
            "big_sur": {
              "url": "https://homebrew.bintray.com/bottles/jq-1.6.big_sur.bottle.1.tar.gz",
              "sha256": "bf0f8577632af7b878b6425476f5b1ab9c3bf66d65affb0c455048a173a0b6bf"
            },
            "catalina": {
              "url": "https://homebrew.bintray.com/bottles/jq-1.6.catalina.bottle.1.tar.gz",
              "sha256": "820a3c85fcbb63088b160c7edf125d7e55fc2c5c1d51569304499c9cc4b89ce8"
            },
            "mojave": {
              "url": "https://homebrew.bintray.com/bottles/jq-1.6.mojave.bottle.1.tar.gz",
              "sha256": "71f0e76c5b22e5088426c971d5e795fe67abee7af6c2c4ae0cf4c0eb98ed21ff"
            },
            "high_sierra": {
              "url": "https://homebrew.bintray.com/bottles/jq-1.6.high_sierra.bottle.1.tar.gz",
              "sha256": "dffcffa4ea13e8f0f2b45c5121e529077e135ae9a47254c32182231662ee9b72"
            },
            "sierra": {
              "url": "https://homebrew.bintray.com/bottles/jq-1.6.sierra.bottle.1.tar.gz",
              "sha256": "bb4d19dc026c2d72c53eed78eaa0ab982e9fcad2cd2acc6d13e7a12ff658e877"
            }
          }
        }
      },
      "mas": {
        "version": "1.8.0",
        "bottle": {
          "rebuild": 0,
          "cellar": ":any",
          "prefix": "/usr/local",
          "root_url": "https://homebrew.bintray.com/bottles",
          "files": {
            "arm64_big_sur": {
              "url": "https://homebrew.bintray.com/bottles/mas-1.8.0.arm64_big_sur.bottle.tar.gz",
              "sha256": "ef2ed904d1283722af006811471484cb1c9c73b255a766b5c0c65ecd1654c8d8"
            },
            "big_sur": {
              "url": "https://homebrew.bintray.com/bottles/mas-1.8.0.big_sur.bottle.tar.gz",
              "sha256": "dc98d69cfa94467e046b443c088a6097fe0ce0d2935e37046815fa3a984a0ca4"
            },
            "catalina": {
              "url": "https://homebrew.bintray.com/bottles/mas-1.8.0.catalina.bottle.tar.gz",
              "sha256": "2e7ffedf674543f98c2b95868b6a23db208cb2e6a3ec1ddbb3553ddab0cf9a68"
            }
          }
        }
      },
      "ncdu": {
        "version": "1.15.1",
        "bottle": {
          "rebuild": 0,
          "cellar": ":any_skip_relocation",
          "prefix": "/usr/local",
          "root_url": "https://homebrew.bintray.com/bottles",
          "files": {
            "arm64_big_sur": {
              "url": "https://homebrew.bintray.com/bottles/ncdu-1.15.1.arm64_big_sur.bottle.tar.gz",
              "sha256": "26eb6537a378702dc900546a2069472b51822fe086f380d0793c29adcc71166f"
            },
            "big_sur": {
              "url": "https://homebrew.bintray.com/bottles/ncdu-1.15.1.big_sur.bottle.tar.gz",
              "sha256": "0761e7d2ca14605c0b5d122521c5f9d63f536fd37bb3cf46ae1367b36d4f166f"
            },
            "catalina": {
              "url": "https://homebrew.bintray.com/bottles/ncdu-1.15.1.catalina.bottle.tar.gz",
              "sha256": "994f7f4e9624a0984ec7c37b5b15b9ae5c24663ebffaba19b0979f4e99919fee"
            },
            "mojave": {
              "url": "https://homebrew.bintray.com/bottles/ncdu-1.15.1.mojave.bottle.tar.gz",
              "sha256": "f7908eaf47c7842b15e56e17279583f4c938a9c920e1bae41f05d3e5506a99fb"
            },
            "high_sierra": {
              "url": "https://homebrew.bintray.com/bottles/ncdu-1.15.1.high_sierra.bottle.tar.gz",
              "sha256": "d094385dbfd71831c5f2b03f0817a06df9471a44f5437aaf577676d2723bc865"
            }
          }
        }
      },
      "skhd": {
        "version": "0.3.5",
        "bottle": false
      },
      "starship": {
        "version": "0.50.0",
        "bottle": {
          "rebuild": 0,
          "cellar": ":any_skip_relocation",
          "prefix": "/usr/local",
          "root_url": "https://homebrew.bintray.com/bottles",
          "files": {
            "arm64_big_sur": {
              "url": "https://homebrew.bintray.com/bottles/starship-0.50.0.arm64_big_sur.bottle.tar.gz",
              "sha256": "992fbc07f611c871359f70e96709cd83527de0eb9b78981e2cf85fa0bf8c09a2"
            },
            "big_sur": {
              "url": "https://homebrew.bintray.com/bottles/starship-0.50.0.big_sur.bottle.tar.gz",
              "sha256": "c4057beb592199c72945960780e133a6bbc0ba8493b3be524a7cb452ecc15611"
            },
            "catalina": {
              "url": "https://homebrew.bintray.com/bottles/starship-0.50.0.catalina.bottle.tar.gz",
              "sha256": "1881da8ab97e614c5a31dc284fa2ed79b911eca4734500f5b81121b164da9953"
            },
            "mojave": {
              "url": "https://homebrew.bintray.com/bottles/starship-0.50.0.mojave.bottle.tar.gz",
              "sha256": "a58de858346930f05259483c254ebecca3d60325145fc1e55f1153b2f4aed266"
            }
          }
        }
      },
      "stow": {
        "version": "2.3.1",
        "bottle": {
          "rebuild": 0,
          "cellar": ":any_skip_relocation",
          "prefix": "/usr/local",
          "root_url": "https://homebrew.bintray.com/bottles",
          "files": {
            "arm64_big_sur": {
              "url": "https://homebrew.bintray.com/bottles/stow-2.3.1.arm64_big_sur.bottle.tar.gz",
              "sha256": "f6dc9f73ac8ef55caa0f8204c893bf41dcdffbae22b39d95a85eee5c99507b55"
            },
            "big_sur": {
              "url": "https://homebrew.bintray.com/bottles/stow-2.3.1.big_sur.bottle.tar.gz",
              "sha256": "e2a4d5cae000bcb2a5464f618b0c1fb174f4c90f66793411ff3c3bdda0438083"
            },
            "catalina": {
              "url": "https://homebrew.bintray.com/bottles/stow-2.3.1.catalina.bottle.tar.gz",
              "sha256": "c99a90dc5e3db8ebcb017df044723fb4e6cce7fb94aa24cf46c8d2c0665bf9a0"
            },
            "mojave": {
              "url": "https://homebrew.bintray.com/bottles/stow-2.3.1.mojave.bottle.tar.gz",
              "sha256": "409987564f7779d6a1db75f64e54c4713ecd9b9e006abac931f8e8d645bdac92"
            },
            "high_sierra": {
              "url": "https://homebrew.bintray.com/bottles/stow-2.3.1.high_sierra.bottle.tar.gz",
              "sha256": "409987564f7779d6a1db75f64e54c4713ecd9b9e006abac931f8e8d645bdac92"
            },
            "sierra": {
              "url": "https://homebrew.bintray.com/bottles/stow-2.3.1.sierra.bottle.tar.gz",
              "sha256": "cbc7a61940a343aff46fdb6190dc26a359d26c9c468c05b1dbde2484a066ceb6"
            }
          }
        }
      },
      "terminal-notifier": {
        "version": "2.0.0",
        "bottle": {
          "rebuild": 0,
          "cellar": ":any_skip_relocation",
          "prefix": "/usr/local",
          "root_url": "https://homebrew.bintray.com/bottles",
          "files": {
            "arm64_big_sur": {
              "url": "https://homebrew.bintray.com/bottles/terminal-notifier-2.0.0.arm64_big_sur.bottle.tar.gz",
              "sha256": "d1268e236f13f5bb4cd5fead9cf54cfb54ceefb98e34861bd39cf3c7e6ef34cf"
            },
            "big_sur": {
              "url": "https://homebrew.bintray.com/bottles/terminal-notifier-2.0.0.big_sur.bottle.tar.gz",
              "sha256": "91f14694ebce08887492aa75138753cd9ff74977868927b15b52559728280055"
            },
            "catalina": {
              "url": "https://homebrew.bintray.com/bottles/terminal-notifier-2.0.0.catalina.bottle.tar.gz",
              "sha256": "78eff95b7436480521ee68a8581ff2df0c615adefccd279486f2491f1b1c0a4b"
            },
            "mojave": {
              "url": "https://homebrew.bintray.com/bottles/terminal-notifier-2.0.0.mojave.bottle.tar.gz",
              "sha256": "9671c602326357b7397248bfb0cf062bc47f19add15b615e512f58545c387c31"
            },
            "high_sierra": {
              "url": "https://homebrew.bintray.com/bottles/terminal-notifier-2.0.0.high_sierra.bottle.tar.gz",
              "sha256": "f112656234f4100d23cc1a41b96f92a09974360a822c2ec0fb6f9970862c1a22"
            },
            "sierra": {
              "url": "https://homebrew.bintray.com/bottles/terminal-notifier-2.0.0.sierra.bottle.tar.gz",
              "sha256": "210cd525fad70bbaef40f092bc3478b1519f68f73c034990230d8b1cc61a8a7c"
            },
            "el_capitan": {
              "url": "https://homebrew.bintray.com/bottles/terminal-notifier-2.0.0.el_capitan.bottle.tar.gz",
              "sha256": "75ce68fd95fb502e20ccb25be72f7db12112ac1a4bdf5a70c140cd174ecbacf5"
            }
          }
        }
      },
      "tmux": {
        "version": "3.1c_1",
        "bottle": {
          "rebuild": 0,
          "cellar": ":any",
          "prefix": "/usr/local",
          "root_url": "https://homebrew.bintray.com/bottles",
          "files": {
            "arm64_big_sur": {
              "url": "https://homebrew.bintray.com/bottles/tmux-3.1c_1.arm64_big_sur.bottle.tar.gz",
              "sha256": "b24cedca1ea1e8e343e5faf6acb509e3df2b3d91b6dcb2934b2c697d8d5b6b07"
            },
            "big_sur": {
              "url": "https://homebrew.bintray.com/bottles/tmux-3.1c_1.big_sur.bottle.tar.gz",
              "sha256": "6f9b667c08719ca7a164c571740d510236d55c922058b1d71fb38f66163a394e"
            },
            "catalina": {
              "url": "https://homebrew.bintray.com/bottles/tmux-3.1c_1.catalina.bottle.tar.gz",
              "sha256": "e1148f3043ef1e77e942bc654e6b3867f40401b0ba93e6d44a460467c51e0a3b"
            },
            "mojave": {
              "url": "https://homebrew.bintray.com/bottles/tmux-3.1c_1.mojave.bottle.tar.gz",
              "sha256": "3ba85f3524acbf5e1fb04135fa9b7f2bbdd5d3c8ed94189685be50ca19722bbe"
            },
            "high_sierra": {
              "url": "https://homebrew.bintray.com/bottles/tmux-3.1c_1.high_sierra.bottle.tar.gz",
              "sha256": "ec5fcbdc337221efdbf3f21121fb087b998dd7d3bf6dd5bb72e352d9c9463a57"
            }
          }
        }
      },
      "watchman": {
        "version": "4.9.0_5",
        "bottle": {
          "rebuild": 0,
          "cellar": "/usr/local/Cellar",
          "prefix": "/usr/local",
          "root_url": "https://homebrew.bintray.com/bottles",
          "files": {
            "arm64_big_sur": {
              "url": "https://homebrew.bintray.com/bottles/watchman-4.9.0_5.arm64_big_sur.bottle.tar.gz",
              "sha256": "4a44a39cfd719b34d146043aa5afcc6ac304ebbd2ff4ff0fb2e37e22871f38ac"
            },
            "big_sur": {
              "url": "https://homebrew.bintray.com/bottles/watchman-4.9.0_5.big_sur.bottle.tar.gz",
              "sha256": "f03c91e17cd7595f98106ee4a27f28433ecc2fd6dde8cc1b7e279bd60b730051"
            },
            "catalina": {
              "url": "https://homebrew.bintray.com/bottles/watchman-4.9.0_5.catalina.bottle.tar.gz",
              "sha256": "30ed7115aa2a2534f5255508915f827c2e6f3100fcd7842415db64e31eabac30"
            },
            "mojave": {
              "url": "https://homebrew.bintray.com/bottles/watchman-4.9.0_5.mojave.bottle.tar.gz",
              "sha256": "135eb0a8f098417a8e4d67bf8d732a19bad1932eee085497877e93982e91074f"
            },
            "high_sierra": {
              "url": "https://homebrew.bintray.com/bottles/watchman-4.9.0_5.high_sierra.bottle.tar.gz",
              "sha256": "e872c3aae64c3b78197de9f12e272bebd5d20c316a120916f59a5f1cd2fac039"
            }
          }
        }
      },
      "yabai": {
        "version": "3.3.7",
        "bottle": false
      },
      "zsh": {
        "version": "5.8_1",
        "bottle": {
          "rebuild": 0,
          "cellar": "/usr/local/Cellar",
          "prefix": "/usr/local",
          "root_url": "https://homebrew.bintray.com/bottles",
          "files": {
            "arm64_big_sur": {
              "url": "https://homebrew.bintray.com/bottles/zsh-5.8_1.arm64_big_sur.bottle.tar.gz",
              "sha256": "01ae59e3ea21dd7691120aec89552e4f4c10c6489a24b9cc23256129e3cbe7b6"
            },
            "big_sur": {
              "url": "https://homebrew.bintray.com/bottles/zsh-5.8_1.big_sur.bottle.tar.gz",
              "sha256": "a93717bcbb1a41829ac7549f7dea0e2be4bb11985be734f03801150338d6b8e6"
            },
            "catalina": {
              "url": "https://homebrew.bintray.com/bottles/zsh-5.8_1.catalina.bottle.tar.gz",
              "sha256": "aaf19f69f79ac2ef80ff31d3b2f0017f400bf40022f8626d5ae046990961a5f5"
            },
            "mojave": {
              "url": "https://homebrew.bintray.com/bottles/zsh-5.8_1.mojave.bottle.tar.gz",
              "sha256": "a40a54e4b686eb75f04e7dcc57391245a4f6b08a39825f7f6ebc9f76ebcbff46"
            },
            "high_sierra": {
              "url": "https://homebrew.bintray.com/bottles/zsh-5.8_1.high_sierra.bottle.tar.gz",
              "sha256": "edfbc09a9571fadf351e0f94e545a88aa33763518a3330c0bae497a6a259d63f"
            }
          }
        }
      }
    },
    "cask": {
      "alacritty": {
        "version": "0.7.2",
        "options": {
          "full_name": "alacritty",
          "args": {
            "appdir": "/Applications"
          }
        }
      },
      "android-file-transfer": {
        "version": "5071136",
        "options": {
          "full_name": "android-file-transfer",
          "args": {
            "appdir": "/Applications"
          }
        }
      },
      "android-studio": {
        "version": "4.1.2.0,201.7042882",
        "options": {
          "full_name": "android-studio",
          "args": {
            "appdir": "/Applications"
          }
        }
      },
      "brave-browser": {
        "version": "89.1.21.74,121.74",
        "options": {
          "full_name": "brave-browser",
          "args": {
            "appdir": "/Applications"
          }
        }
      },
      "discord": {
        "version": "0.0.261",
        "options": {
          "full_name": "discord",
          "args": {
            "appdir": "/Applications"
          }
        }
      },
      "figma": {
        "version": "95.7.0",
        "options": {
          "full_name": "figma",
          "args": {
            "appdir": "/Applications"
          }
        }
      },
      "font-roboto": {
        "version": "latest",
        "options": {
          "full_name": "font-roboto",
          "args": {
            "appdir": "/Applications"
          }
        }
      },
      "font-roboto-mono": {
        "version": "latest",
        "options": {
          "full_name": "font-roboto-mono",
          "args": {
            "appdir": "/Applications"
          }
        }
      },
      "google-chrome": {
        "version": "89.0.4389.82,4389.82",
        "options": {
          "full_name": "google-chrome",
          "args": {
            "appdir": "/Applications"
          }
        }
      },
      "google-japanese-ime": {
        "version": "latest",
        "options": {
          "full_name": "google-japanese-ime",
          "args": {
            "appdir": "/Applications"
          }
        }
      },
      "gpg-suite": {
        "version": "2020.2",
        "options": {
          "full_name": "gpg-suite",
          "args": {
            "appdir": "/Applications"
          }
        }
      },
      "ledger-live": {
        "version": "2.23.0",
        "options": {
          "full_name": "ledger-live",
          "args": {
            "appdir": "/Applications"
          }
        }
      },
      "minecraft": {
        "version": "883,1",
        "options": {
          "full_name": "minecraft",
          "args": {
            "appdir": "/Applications"
          }
        }
      },
      "obs": {
        "version": "26.1.2",
        "options": {
          "full_name": "obs",
          "args": {
            "appdir": "/Applications"
          }
        }
      },
      "postman": {
        "version": "8.0.7",
        "options": {
          "full_name": "postman",
          "args": {
            "appdir": "/Applications"
          }
        }
      },
      "react-native-debugger": {
        "version": "0.11.7",
        "options": {
          "full_name": "react-native-debugger",
          "args": {
            "appdir": "/Applications"
          }
        }
      },
      "signal": {
        "version": "1.40.1",
        "options": {
          "full_name": "signal",
          "args": {
            "appdir": "/Applications"
          }
        }
      },
      "slack": {
        "version": "4.13.0",
        "options": {
          "full_name": "slack",
          "args": {
            "appdir": "/Applications"
          }
        }
      },
      "steam": {
        "version": "2021-02-13",
        "options": {
          "full_name": "steam",
          "args": {
            "appdir": "/Applications"
          }
        }
      },
      "virtualbox": {
        "version": "6.1.18,142142",
        "options": {
          "full_name": "virtualbox",
          "args": {
            "appdir": "/Applications"
          }
        }
      },
      "visual-studio-code": {
        "version": "1.54.1",
        "options": {
          "full_name": "visual-studio-code",
          "args": {
            "appdir": "/Applications"
          }
        }
      },
      "zoom": {
        "version": "5.5.13148.0305",
        "options": {
          "full_name": "zoom",
          "args": {
            "appdir": "/Applications"
          }
        }
      },
      "notion": {
        "version": "2.0.15",
        "options": {
          "full_name": "notion",
          "args": {
            "appdir": "/Applications"
          }
        }
      }
    },
    "mas": {
      "Xcode": {
        "id": "497799835",
        "version": "12.4"
      },
      "Final Cut Pro": {
        "id": "424389933",
        "version": "10.5.2"
      },
      "Simple Recorder-Voice Recorder": null
    }
  },
  "system": {
    "macos": {
      "catalina": {
        "HOMEBREW_VERSION": "3.0.4",
        "HOMEBREW_PREFIX": "/usr/local",
        "Homebrew/homebrew-core": "3cde08c142d6f0005fb0f4fcd953e65f86eca593",
        "CLT": "11.0.33.17",
        "Xcode": "12.4",
        "macOS": "10.15.7"
      }
    }
  }
}
